hitac/__init__.py
hitac/_qiime.py
hitac/_utils.py
hitac/_version.py
hitac/citations.bib
hitac/filter.py
hitac/hitac_classify.py
hitac/hitac_filter.py
hitac/hitac_fit.py
hitac/hitac_fit_filter.py
hitac/plugin_setup.py
hitac/qiime.py
hitac-2.2.2.dist-info/LICENSE
hitac-2.2.2.dist-info/METADATA
hitac-2.2.2.dist-info/WHEEL
hitac-2.2.2.dist-info/entry_points.txt
hitac-2.2.2.dist-info/top_level.txt
hitac-2.2.2.dist-info/RECORD
