Metadata-Version: 2.1
Name: hitac
Version: 2.2.2
Summary: Hierarchical taxonomic classifier.
Author: Fabio Malcher Miranda
Author-email: fabio.malchermiranda@hpi.de
License: BSD 3-Clause
Project-URL: Bug Tracker, https://gitlab.com/dacs-hpi/hitac/-/issues
Project-URL: Source Code, https://gitlab.com/dacs-hpi/hitac
Project-URL: Related Software, https://gitlab.com/dacs-hpi
Keywords: hierarchical taxonomic classifier
Classifier: Programming Language :: Python
Classifier: Programming Language :: Python :: 3.8
Classifier: Programming Language :: Python :: Implementation :: PyPy
Classifier: License :: OSI Approved
Requires-Python: >=3.8
License-File: LICENSE
Requires-Dist: pandas
Requires-Dist: numpy
Requires-Dist: scikit-learn
Requires-Dist: hiclass
Requires-Dist: scikit-bio
Provides-Extra: dev
Requires-Dist: pytest ; extra == 'dev'
Requires-Dist: flake8 ; extra == 'dev'
Requires-Dist: pydocstyle ; extra == 'dev'
Requires-Dist: pytest-cov ; extra == 'dev'
Requires-Dist: pre-commit ; extra == 'dev'
Requires-Dist: pyfakefs ; extra == 'dev'
